hello_pkg/__init__.py
hello_pkg/hello.py
pkghellosj-0.0.1.dist-info/METADATA
pkghellosj-0.0.1.dist-info/WHEEL
pkghellosj-0.0.1.dist-info/top_level.txt
pkghellosj-0.0.1.dist-info/RECORD
